iceprod/__init__.py
iceprod/client_auth.py
iceprod/py.typed
iceprod/roles_groups.py
iceprod/s3.py
iceprod/util.py
iceprod/common/mongo.py
iceprod/common/mongo_queue.py
iceprod/common/prom_utils.py
iceprod/core/__init__.py
iceprod/core/config.py
iceprod/core/dataclasses.py
iceprod/core/defaults.py
iceprod/core/exe.py
iceprod/core/file_catalog.py
iceprod/core/functions.py
iceprod/core/gridftp.py
iceprod/core/i3exec.py
iceprod/core/jsonUtil.py
iceprod/core/logger.py
iceprod/core/parser.py
iceprod/core/resources.py
iceprod/core/util.py
iceprod/core/data/dataset_v3.1.schema.json
iceprod/core/data/dataset_v3.2.schema.json
iceprod/credentials/__init__.py
iceprod/credentials/__main__.py
iceprod/credentials/client.py
iceprod/credentials/server.py
iceprod/credentials/service.py
iceprod/credentials/util.py
iceprod/credentials/data/credentials.schema.json
iceprod/modules/__init__.py
iceprod/rest/__init__.py
iceprod/rest/__main__.py
iceprod/rest/auth.py
iceprod/rest/base_handler.py
iceprod/rest/config.py
iceprod/rest/server.py
iceprod/rest/handlers/__init__.py
iceprod/rest/handlers/auth.py
iceprod/rest/handlers/config.py
iceprod/rest/handlers/datasets.py
iceprod/rest/handlers/grids.py
iceprod/rest/handlers/jobs.py
iceprod/rest/handlers/logs.py
iceprod/rest/handlers/task_stats.py
iceprod/rest/handlers/tasks.py
iceprod/scheduled_tasks/__init__.py
iceprod/scheduled_tasks/buffer_jobs_tasks.py
iceprod/scheduled_tasks/dataset_cleanup.py
iceprod/scheduled_tasks/dataset_completion.py
iceprod/scheduled_tasks/dataset_monitor.py
iceprod/scheduled_tasks/job_completion.py
iceprod/scheduled_tasks/job_temp_cleaning.py
iceprod/scheduled_tasks/log_cleanup.py
iceprod/scheduled_tasks/queue_tasks.py
iceprod/scheduled_tasks/update_task_priority.py
iceprod/server/__init__.py
iceprod/server/config.py
iceprod/server/daemon.py
iceprod/server/dataset_prio.py
iceprod/server/documentation.py
iceprod/server/globus.py
iceprod/server/grid.py
iceprod/server/priority.py
iceprod/server/queue.py
iceprod-3.2.12.dist-info/licenses/LICENSE
iceprod-3.2.12.dist-info/METADATA
iceprod-3.2.12.dist-info/WHEEL
iceprod-3.2.12.dist-info/top_level.txt
iceprod-3.2.12.dist-info/RECORD
