Metadata-Version: 2.4
Name: iceprod
Version: 3.2.12
Summary: IceCube dataset management system
Author-email: WIPAC Developers <developers@icecube.wisc.edu>
License-Expression: MIT
Project-URL: Homepage, https://pypi.org/project/iceprod/
Project-URL: Tracker, https://github.com/WIPACrepo/iceprod/issues
Project-URL: Source, https://github.com/WIPACrepo/iceprod
Keywords: WIPAC,batch,workload
Classifier: Programming Language :: Python :: 3.12
Classifier: Programming Language :: Python :: 3.13
Classifier: Programming Language :: Python :: 3.14
Requires-Python: <3.15,>=3.12
License-File: LICENSE
Requires-Dist: PyYAML
Requires-Dist: asyncache
Requires-Dist: boto3<1.36
Requires-Dist: cachetools
Requires-Dist: certifi
Requires-Dist: cryptography
Requires-Dist: htcondor>=25.3.1
Requires-Dist: httpx
Requires-Dist: jsonschema
Requires-Dist: ldap3
Requires-Dist: prometheus-client
Requires-Dist: psutil
Requires-Dist: pymongo>=4.13
Requires-Dist: python-dateutil
Requires-Dist: requests
Requires-Dist: requests-futures
Requires-Dist: requests-toolbelt
Requires-Dist: setproctitle
Requires-Dist: tornado
Requires-Dist: unidecode
Requires-Dist: wipac-dev-tools
Requires-Dist: wipac-rest-tools[redis]>=1.12.2
Provides-Extra: tests
Requires-Dist: beautifulsoup4; extra == "tests"
Requires-Dist: coverage; extra == "tests"
Requires-Dist: flake8; extra == "tests"
Requires-Dist: flexmock; extra == "tests"
Requires-Dist: mock; extra == "tests"
Requires-Dist: moto[s3]>=5; extra == "tests"
Requires-Dist: pytest-asyncio; extra == "tests"
Requires-Dist: pytest-cov; extra == "tests"
Requires-Dist: pytest-mock; extra == "tests"
Requires-Dist: pytest<8.1; extra == "tests"
Requires-Dist: requests-mock; extra == "tests"
Requires-Dist: respx; extra == "tests"
Requires-Dist: types-cachetools; extra == "tests"
Requires-Dist: types-requests; extra == "tests"
Provides-Extra: docs
Requires-Dist: sphinx<9; extra == "docs"
Provides-Extra: mypy
Requires-Dist: beautifulsoup4; extra == "mypy"
Requires-Dist: coverage; extra == "mypy"
Requires-Dist: flake8; extra == "mypy"
Requires-Dist: flexmock; extra == "mypy"
Requires-Dist: mock; extra == "mypy"
Requires-Dist: moto[s3]>=5; extra == "mypy"
Requires-Dist: pytest-asyncio; extra == "mypy"
Requires-Dist: pytest-cov; extra == "mypy"
Requires-Dist: pytest-mock; extra == "mypy"
Requires-Dist: pytest<8.1; extra == "mypy"
Requires-Dist: requests-mock; extra == "mypy"
Requires-Dist: respx; extra == "mypy"
Requires-Dist: sphinx<9; extra == "mypy"
Requires-Dist: types-cachetools; extra == "mypy"
Requires-Dist: types-requests; extra == "mypy"
Dynamic: license-file
